{
	"required": true,
	"minVersion": "0.8",
	"package": "io.github.antikyth.searchable.mixin",
	"compatibilityLevel": "JAVA_17",
	"mixins": [
		"gamerule.GameRules$CategoryMixin",
		"pack.PackListWidgetMixin",
		"select_world.WorldSaveSummaryMixin"
	],
	"client": [
		"ClickableWidgetMixin",
		"EntryListWidgetMixin",
		"TextFieldWidgetMixin",
		"gamerule.AbstractRuleWidgetMixin",
		"gamerule.BooleanRuleWidgetMixin",
		"gamerule.EditGameRulesScreenMixin",
		"gamerule.IntRuleWidgetMixin",
		"gamerule.NamedRuleWidgetMixin",
		"gamerule.RuleCategoryWidgetMixin",
		"gamerule.RuleListWidgetMixin",
		"keybind.KeyBindEntryMixin",
		"keybind.KeyBindListWidgetMixin",
		"keybind.KeyBindMixin",
		"keybind.KeyBindsScreenMixin",
		"language.LanguageEntryMixin",
		"language.LanguageOptionsScreenMixin",
		"language.LanguageSelectionListWidgetMixin",
		"pack.PackScreenMixin",
		"pack.ResourcePackEntryMixin",
		"select_server.LanServerEntryMixin",
		"select_server.MultiplayerScreenMixin",
		"select_server.MultiplayerServerListWidgetMixin",
		"select_server.ServerEntryMixin",
		"select_world.SelectWorldScreenMixin",
		"select_world.WorldListWidget$EntryMixin",
		"select_world.WorldListWidgetMixin"
	],
	"injectors": {
		"defaultRequire": 1
	}
}
